aiogram_unittest/__init__.py
aiogram_unittest/args_parser.py
aiogram_unittest/handler.py
aiogram_unittest/requester.py
aiogram_unittest/utils.py
aiogram_unittest/types/__init__.py
aiogram_unittest/types/dataset/__init__.py
aiogram_unittest/types/dataset/base.py
aiogram_unittest-0.0.1.dist-info/LICENSE
aiogram_unittest-0.0.1.dist-info/METADATA
aiogram_unittest-0.0.1.dist-info/WHEEL
aiogram_unittest-0.0.1.dist-info/top_level.txt
aiogram_unittest-0.0.1.dist-info/RECORD
