Metadata-Version: 2.1
Name: aiogram_unittest
Version: 0.0.1
Summary: A library for unittesting your bots on aiogram
Author-email: Timur <pavlov.timur556@yandex.ru>
Project-URL: Homepage, https://github.com/OCCCAS/aiogram_unittest
Classifier: Programming Language :: Python :: 3
Classifier: License :: OSI Approved :: MIT License
Classifier: Operating System :: OS Independent
License-File: LICENSE
